simenv/__init__.py
simenv/core/__init__.py
simenv/core/node.py
simenv/core/scene.py
simenv/core/view.py
simenv-0.0.1.dev0.dist-info/LICENSE
simenv-0.0.1.dev0.dist-info/METADATA
simenv-0.0.1.dev0.dist-info/WHEEL
simenv-0.0.1.dev0.dist-info/top_level.txt
simenv-0.0.1.dev0.dist-info/RECORD
