Metadata-Version: 2.1
Name: simenv
Version: 0.0.1.dev0
Summary: HuggingFace community-driven open-source library of simulation environments
Home-page: https://github.com/huggingface/simenv
Download-URL: https://github.com/huggingface/simenv/tags
Author: HuggingFace Inc.
Author-email: thomas@huggingface.co
License: Apache 2.0
Keywords: simulation environments synthetic data datasets machine learning
Platform: UNKNOWN
Classifier: Development Status :: 5 - Production/Stable
Classifier: Intended Audience :: Developers
Classifier: Intended Audience :: Education
Classifier: Intended Audience :: Science/Research
Classifier: License :: OSI Approved :: Apache Software License
Classifier: Operating System :: OS Independent
Classifier: Programming Language :: Python :: 3
Classifier: Programming Language :: Python :: 3.6
Classifier: Programming Language :: Python :: 3.7
Classifier: Programming Language :: Python :: 3.8
Classifier: Programming Language :: Python :: 3.9
Classifier: Programming Language :: Python :: 3.10
Classifier: Topic :: Scientific/Engineering :: Artificial Intelligence
License-File: LICENSE
Requires-Dist: numpy (>=1.17)
Provides-Extra: dev
Requires-Dist: black (~=22.0) ; extra == 'dev'
Requires-Dist: flake8 (>=3.8.3) ; extra == 'dev'
Requires-Dist: isort (>=5.0.0) ; extra == 'dev'
Requires-Dist: pyyaml (>=5.3.1) ; extra == 'dev'
Provides-Extra: quality
Requires-Dist: black (~=22.0) ; extra == 'quality'
Requires-Dist: flake8 (>=3.8.3) ; extra == 'quality'
Requires-Dist: isort (>=5.0.0) ; extra == 'quality'
Requires-Dist: pyyaml (>=5.3.1) ; extra == 'quality'
Provides-Extra: tests
